movie_magnet/__init__.py
movie_magnet/__main__.py
movie_magnet-0.0.3.dist-info/METADATA
movie_magnet-0.0.3.dist-info/WHEEL
movie_magnet-0.0.3.dist-info/entry_points.txt
movie_magnet-0.0.3.dist-info/top_level.txt
movie_magnet-0.0.3.dist-info/RECORD
