Metadata-Version: 2.1
Name: movie-magnet
Version: 0.0.3
Summary: Python tool to get magnet links to any movie
Home-page: https://github.com/zahash/movie_magnet
Author: zahash
Author-email: zahash.z@gmail.com
License: MIT
Platform: UNKNOWN
Classifier: License :: OSI Approved :: MIT License
Classifier: Programming Language :: Python :: 3
Classifier: Programming Language :: Python :: 3.7
Requires-Dist: bs4
Requires-Dist: requests
Requires-Dist: pandas
Requires-Dist: tabulate
Requires-Dist: termcolor
Requires-Dist: pyfiglet
Requires-Dist: lxml
